pyspeedinsights/__init__.py
pyspeedinsights/__main__.py
pyspeedinsights/app.py
pyspeedinsights/api/__init__.py
pyspeedinsights/api/keys.py
pyspeedinsights/api/request.py
pyspeedinsights/api/response.py
pyspeedinsights/cli/__init__.py
pyspeedinsights/cli/choices.py
pyspeedinsights/cli/commands.py
pyspeedinsights/core/__init__.py
pyspeedinsights/core/excel.py
pyspeedinsights/core/sitemap.py
pyspeedinsights/utils/__init__.py
pyspeedinsights/utils/generic.py
pyspeedinsights/utils/urls.py
pyspeedinsights-0.5.1.dist-info/LICENSE
pyspeedinsights-0.5.1.dist-info/METADATA
pyspeedinsights-0.5.1.dist-info/WHEEL
pyspeedinsights-0.5.1.dist-info/entry_points.txt
pyspeedinsights-0.5.1.dist-info/top_level.txt
pyspeedinsights-0.5.1.dist-info/RECORD
