Metadata-Version: 2.1
Name: pyspeedinsights
Version: 0.5.1
Summary: Measure your site speed, performance, accessibility and SEO in bulk from the command line with Python and the PageSpeed Insights API.
Home-page: https://github.com/wjh18/pyspeedinsights
Author: Will J. Holmes
Author-email: will@wjholmes.com
Project-URL: Documentation, https://github.com/wjh18/pyspeedinsights/blob/master/README.md
Project-URL: Source, https://github.com/wjh18/pyspeedinsights
Project-URL: Tracker, https://github.com/wjh18/pyspeedinsights/issues
Keywords: google,google-apis,psi-api,page-speed-insights,page-speed-insights-api,pagespeedinsightsapi,python,cli
Classifier: Programming Language :: Python :: 3
Classifier: Programming Language :: Python :: 3 :: Only
Classifier: Programming Language :: Python :: 3.9
Classifier: Programming Language :: Python :: 3.10
Classifier: License :: OSI Approved :: MIT License
Classifier: Operating System :: OS Independent
Classifier: Intended Audience :: End Users/Desktop
Classifier: Topic :: Internet :: WWW/HTTP :: Site Management
Classifier: Topic :: Utilities
Requires-Python: >=3.9
License-File: LICENSE
Requires-Dist: requests
Requires-Dist: XlsxWriter
Requires-Dist: keyring
Requires-Dist: aiohttp[speedups]
Requires-Dist: defusedxml
Provides-Extra: dev
Requires-Dist: pytest ; extra == 'dev'
Requires-Dist: pytest-cov ; extra == 'dev'
Requires-Dist: pytest-datadir ; extra == 'dev'
Requires-Dist: flake8 ; extra == 'dev'
Requires-Dist: isort ; extra == 'dev'
Requires-Dist: black ; extra == 'dev'
Requires-Dist: bandit ; extra == 'dev'
Requires-Dist: pre-commit ; extra == 'dev'
Requires-Dist: mypy ; extra == 'dev'
Requires-Dist: types-requests ; extra == 'dev'
